[
    {
        "marca": "Audi",
        "modelo": "A4",
        "nuevo": true,
        "concesionario": "641adb6372e341ea86c93005",
        "motor": "Gasolina",
        "transmision": "Automatica",
        "cilindrada": 220,
        "carroceria": "Deportivo",
        "precio": 40000,
        "foto": "https://cdn-images.motor.es/image/m/756w504h.webp/fotos-jato/audi/uploads/audi-a4-63dc311657037.jpg"
    },
    {
        "marca": "Audi",
        "modelo": "A3",
        "nuevo": true,
        "concesionario": "641adb6372e341ea86c93006",
        "motor": "Gasolina",
        "transmision": "Automatica",
        "cilindrada": 240,
        "carroceria": "Deportivo",
        "precio": 38000,
        "foto": "https://www.autobild.es/sites/autobild.es/public/styles/855/public/dc/fotos/Audi_A3_2020.jpg?itok=cSjo_X9r"
    },
    {
        "marca": "Peugot",
        "modelo": "208",
        "nuevo": true,
        "concesionario": "641adb6372e341ea86c93007",
        "motor": "Electrico",
        "transmision": "Automatica",
        "cilindrada": 120,
        "carroceria": "Suv",
        "precio": 38890,
        "foto": "https://images.coches.com/_vn_/peugeot/208/3446993b14eed579dd814da7d1bd77eb.jpg?p=cc_vn_high"
    },
    {
        "marca": "Renault",
        "modelo": "Laguna",
        "nuevo": true,
        "concesionario": "641adb6372e341ea86c93008",
        "motor": "Gasolina",
        "transmision": "Manual",
        "cilindrada": 100,
        "carroceria": "Urbano",
        "precio": 19950,
        "foto": "https://e00-elmundo.uecdn.es/elmundomotor/imagenes/2007/06/04/1180975643_extras_noticia_1_0.jpg"
    },
    {
        "marca": "Audi",
        "modelo": "A6",
        "nuevo": true,
        "concesionario": "641adb6372e341ea86c93009",
        "motor": "Gasolina",
        "transmision": "Automatica",
        "cilindrada": 310,
        "carroceria": "Deportivo",
        "precio": 59000,
        "foto": "https://www.audi.es/content/dam/nemo/es/modelos/a6/a6/my-2022/derivative-startpage/stage/1920x1080-AA6_L_181012_2.jpg?imwidth=1920"
    },
    {
        "marca": "Renaul",
        "modelo": "Clio",
        "nuevo": true,
        "concesionario": "641adb6372e341ea86c9300a",
        "motor": "Diesel",
        "transmision": "Manual",
        "cilindrada": 200,
        "carroceria": "Urbano",
        "precio": 39000,
        "foto": "https://images.coches.com/_vn_/renault/Clio/674171eb98d8b108125eca298fbd5735.jpg?p=cc_vn_high"
    },
    {
        "marca": "Chevrolete",
        "modelo": "Camaro",
        "nuevo": true,
        "concesionario": "641adb6372e341ea86c9300b",
        "motor": "Gasolina",
        "transmision": "Automatica",
        "cilindrada": 500,
        "carroceria": "Descapotable",
        "precio": 79890,
        "foto": "https://www.chevrolet.com/content/dam/chevrolet/na/us/english/index/vehicles/2023/performance/camaro/01-images/colorizer/2023-camaro-2ss-g7c-colorizer.jpg?imwidth=600"
    },
    {
        "marca": "Dacia",
        "modelo": "Duster",
        "nuevo": true,
        "concesionario": "641adb6372e341ea86c9300c",
        "motor": "Hibrido",
        "transmision": "Automatica",
        "cilindrada": 150,
        "carroceria": "Suv",
        "precio": 25000,
        "foto": "https://cdn.group.renault.com/dac/master/dacia-vn/vehicules/duster/hjd-duster/hjd-duster-ph2/edito-2560-x-1440/dacia-duster-hjd-ph2-003.jpg.ximg.mediumx2.webp/087850f91d.webp"
    },
    {
        "marca": "Range Rover",
        "modelo": "Velar",
        "nuevo": true,
        "concesionario": "641adb6372e341ea86c9300d",
        "motor": "Gasolina",
        "transmision": "Automatica",
        "cilindrada": 240,
        "carroceria": "Todoterreno",
        "precio": 46000,
        "foto": "https://cdn-images.motor.es/image/m/694w.webp/fotos-noticias/2023/02/range-rover-velar-2023-202392727-1675246010_1.jpg"
    },
    {
        "marca": "Citroen",
        "modelo": "A3",
        "nuevo": true,
        "concesionario": "641adb6372e341ea86c9300e",
        "motor": "Gasolina",
        "transmision": "Manual",
        "cilindrada": 200,
        "carroceria": "Urbano",
        "precio": 38000,
        "foto": "https://imagenes.km77.com/fotos/bbtcontent/clippingnew/KM7KPH20100930_0072/full.jpg?_gl=1*trota6*_ga*ODQzMTQzOTYwLjE2Nzk0ODM1NjI.*_ga_6YFP9YXPMX*MTY3OTQ4MzU2MS4xLjAuMTY3OTQ4MzU2MS42MC4wLjA."
    },
    {
        "marca": "Seat",
        "modelo": "Leon",
        "nuevo": true,
        "concesionario": "641adb6372e341ea86c9300f",
        "motor": "Electrico",
        "transmision": "Automatica",
        "cilindrada": 260,
        "carroceria": "Deportivo",
        "precio": 39000,
        "foto": "https://www.seat.es/content/dam/public/seat-website/myco/2325/carworlds/leon/overview/version-view/leon-style/seat-leon-5d-midnight-black-style-trim-colour-alloy-wheels.png"
    },
    {
        "marca": "Citroen",
        "modelo": "Grand C4 SpaceTourer",
        "nuevo": true,
        "concesionario": "641adb6372e341ea86c93010",
        "motor": "Gasolina",
        "transmision": "Manual",
        "cilindrada": 130,
        "carroceria": "Monovolumen",
        "precio": 27500,
        "foto": "https://motor.elpais.com/wp-content/uploads/2020/06/citroen-1046x616.jpg"
    },
    {
        "marca": "Tesla",
        "modelo": "Roadster",
        "nuevo": true,
        "concesionario": "641adb6372e341ea86c93011",
        "motor": "Electrico",
        "transmision": "Automatica",
        "cilindrada": 240,
        "carroceria": "Roadster",
        "precio": 57000,
        "foto": "https://img.remediosdigitales.com/2b322f/1366_2000-6/1366_2000.jpg"
    },
    {
        "marca": "BMW",
        "modelo": "Serie 4",
        "nuevo": true,
        "concesionario": "641adb6372e341ea86c93012",
        "motor": "Gasolina",
        "transmision": "Automatica",
        "cilindrada": 320,
        "carroceria": "Coupe",
        "precio": 61000,
        "foto": "https://s3.ppllstatics.com/diariovasco/www/multimedia/202007/03/media/cortadas/BMW-Serie4-kNK-U110697958968yGC-624x385@RC.jpg"
    },
    {
        "marca": "Golf",
        "modelo": "Gti",
        "nuevo": true,
        "concesionario": "641adb6372e341ea86c93013",
        "motor": "Gasolina",
        "transmision": "Manual",
        "cilindrada": 240,
        "carroceria": "Hatchback",
        "precio": 38500,
        "foto": "https://images0.autocasion.com/unsafe/640x480/actualidad/wp-content/uploads/2016/07/el-hacth-tiene-integrado-el-maletero-en-el-habitaculo_aper.jpg"
    },
    {
        "marca": "Toyota",
        "modelo": "Hilux",
        "nuevo": true,
        "concesionario": "641adb6372e341ea86c93014",
        "motor": "Gasolina",
        "transmision": "Manual",
        "cilindrada": 200,
        "carroceria": "Pickup",
        "precio": 35000,
        "foto": "https://fotografias.lasexta.com/clipping/cmsimages01/2020/10/27/5BBE616B-A06F-4ED4-9DEA-440368BC5A2C/97.jpg?crop=1595,897,x5,y0&width=1600&height=900&optimize=high&format=webply"
    },
    {
        "marca": "Toyota",
        "modelo": "ProAce",
        "nuevo": true,
        "concesionario": "641adb6372e341ea86c93015",
        "motor": "Gasolina",
        "transmision": "Manual",
        "cilindrada": 215,
        "carroceria": "Furgoneta",
        "precio": 25000,
        "foto": "https://www.autobild.es/sites/autobild.es/public/styles/main_element/public/dc/fotos/Toyota_ProAce_2016_01.jpg?itok=cxw4a31S"
    },
    {
        "marca": "Volvo",
        "modelo": "s90",
        "nuevo": true,
        "concesionario": "641adb6372e341ea86c93016",
        "motor": "Gasolina",
        "transmision": "Automatica",
        "cilindrada": 180,
        "carroceria": "Sedan",
        "precio": 26000,
        "foto": "https://www.autobild.es/sites/autobild.es/public/styles/main_element/public/dc/fotos/Volvo-S90_2017_C01.jpg?itok=__fzljV6"
    },
    {
        "marca": "Seat",
        "modelo": "Ibiza",
        "nuevo": true,
        "concesionario": "641adb6372e341ea86c93017",
        "motor": "Hibrido",
        "transmision": "Automatica",
        "cilindrada": 175,
        "carroceria": "Urbano",
        "precio": 27500,
        "foto": "https://sp-ao.shortpixel.ai/client/to_webp,q_glossy,ret_img,w_1024,h_600/https://www.grupogil.es/wp-content/uploads/2019/07/SEAT_IBIZATGI-876x535.jpg"
    }
]